etcdproxy/__init__.py
etcdproxy/url_parser.py
etcdproxy-0.0.2.dist-info/LICENSE
etcdproxy-0.0.2.dist-info/METADATA
etcdproxy-0.0.2.dist-info/WHEEL
etcdproxy-0.0.2.dist-info/top_level.txt
etcdproxy-0.0.2.dist-info/RECORD
