Metadata-Version: 2.1
Name: etcdproxy
Version: 0.0.2
Summary: etcd的代理对象
Author: hsz
Author-email: hsz1273327@gmail.com
License: MIT License
Keywords: etcd,proxy,asyncio
Classifier: License :: OSI Approved :: MIT License
Classifier: Programming Language :: Python :: 3.8
Classifier: Programming Language :: Python :: 3.9
Classifier: Programming Language :: Python :: 3.10
License-File: LICENSE
Requires-Dist: etcd3 (>=0.12.0)
Requires-Dist: aetcd (>=1.0.0a2)
Requires-Dist: pyproxypattern (>=0.0.1)
